lovelanguage/__init__.py
lovelanguage/schemas/__init__.py
lovelanguage/schemas/use-of-force.schema.json
lovelanguage-0.1.0.dist-info/METADATA
lovelanguage-0.1.0.dist-info/WHEEL
lovelanguage-0.1.0.dist-info/RECORD
