Metadata-Version: 2.1
Name: lovelanguage
Version: 0.1.0
Summary: An importable collection of JSON schemas for Human betterment.
License: LGPL-3.0-or-later
Author: 'Jurnell Cockhren'
Author-email: jurnell@civichacker.com
Requires-Python: >=3.8,<4.0
Classifier: License :: OSI Approved :: GNU Lesser General Public License v3 or later (LGPLv3+)
Classifier: Programming Language :: Python :: 3
Classifier: Programming Language :: Python :: 3.8
Classifier: Programming Language :: Python :: 3.9
Classifier: Programming Language :: Python :: 3.10
Classifier: Programming Language :: Python :: 3.11
